zaius/__init__.py
zaius/s3.py
zaius/auth/__init__.py
zaius/auth/auth.py
zaius/cli/__init__.py
zaius/cli/main.py
zaius/export/__init__.py
zaius/export/api.py
zaius/export/parser.py
zaius/reports/__init__.py
zaius/reports/demo.py
zaius/reports/email_metrics.py
zaius/reports/lifecycle_progress.py
zaius/reports/product_attribution.py
zaius/reports/spec.py
zaius/tests/__init__.py
zaius/tests/test_parser.py
zaius/tests/test_reports.py
zaius_export-1.5.dist-info/LICENSE
zaius_export-1.5.dist-info/METADATA
zaius_export-1.5.dist-info/WHEEL
zaius_export-1.5.dist-info/entry_points.txt
zaius_export-1.5.dist-info/top_level.txt
zaius_export-1.5.dist-info/RECORD
