Metadata-Version: 2.1
Name: zaius-export
Version: 1.5
Summary: Zaius Export API Interface
Home-page: http://github.com/zaiusinc/python-zaius-export
Author: The Zaius Team
Author-email: engineering@zaius.com
License: Apache 2.0
Platform: UNKNOWN
Classifier: Programming Language :: Python :: 3
Classifier: License :: OSI Approved :: MIT License
Classifier: Operating System :: OS Independent
Requires-Dist: requests
Requires-Dist: parsy
Requires-Dist: boto3 (>=1.12)
Requires-Dist: python-dateutil (==2.8.0)
